ggdtest/__init__.py
ggdtest/decorators/singleton.py
ggdtest/utils/dialog.py
ggdtest-0.1.2.dist-info/WHEEL
ggdtest-0.1.2.dist-info/entry_points.txt
ggdtest-0.1.2.dist-info/METADATA
ggdtest-0.1.2.dist-info/RECORD
