Metadata-Version: 2.3
Name: ggdtest
Version: 0.1.2
Summary: Add your description here
Author: lipanpanx
Author-email: lipanpanx <47287977+lipanpan-hub@users.noreply.github.com>
Requires-Dist: fire>=0.7.1
Requires-Python: >=3.13
